que/__about__.py
que/__init__.py
que/query.py
que/util.py
que_py-1.1.1.dist-info/LICENSE
que_py-1.1.1.dist-info/METADATA
que_py-1.1.1.dist-info/WHEEL
que_py-1.1.1.dist-info/top_level.txt
que_py-1.1.1.dist-info/RECORD
